plca/__init__.py
plca/__main__.py
plca/__version__.py
plca/elcd.json
plca/plca.py
plca/__pycache__/__version__.cpython-38.pyc
plca-1.0.2.dist-info/LICENSE.txt
plca-1.0.2.dist-info/METADATA
plca-1.0.2.dist-info/WHEEL
plca-1.0.2.dist-info/top_level.txt
plca-1.0.2.dist-info/RECORD
